lenz_flashtool/__init__.py
lenz_flashtool/biss/__init__.py
lenz_flashtool/biss/cli.py
lenz_flashtool/biss/commands.py
lenz_flashtool/biss/crc.py
lenz_flashtool/biss/registers.py
lenz_flashtool/encproc/__init__.py
lenz_flashtool/encproc/processing.py
lenz_flashtool/flashtool/__init__.py
lenz_flashtool/flashtool/core.py
lenz_flashtool/flashtool/errors.py
lenz_flashtool/flashtool/ft_bl_connection.py
lenz_flashtool/flashtool/hex_generator.py
lenz_flashtool/flashtool/hex_utils.py
lenz_flashtool/flashtool/logging.py
lenz_flashtool/flashtool/operations.py
lenz_flashtool/flashtool/uart.py
lenz_flashtool/testing/__init__.py
lenz_flashtool/testing/mock_flashtool.py
lenz_flashtool/utils/__init__.py
lenz_flashtool/utils/plot.py
lenz_flashtool/utils/progress.py
lenz_flashtool/utils/termcolors.py
lenz_flashtool-0.1.8.dist-info/METADATA
lenz_flashtool-0.1.8.dist-info/WHEEL
lenz_flashtool-0.1.8.dist-info/entry_points.txt
lenz_flashtool-0.1.8.dist-info/licenses/LICENSE
lenz_flashtool-0.1.8.dist-info/RECORD
