Metadata-Version: 2.4
Name: lenz-flashtool
Version: 0.1.8
Summary: FlashTool library for BiSS C Firmware Update and Calibration by LENZ Encoders
Project-URL: Homepage, https://github.com/lenzencoders/lenz-flashtool-lib
Project-URL: Source, https://github.com/lenzencoders/lenz-flashtool-lib
Project-URL: Documentation, https://flashtool.lenzencoders.com
Author-email: LENZ ENCODERS <devs@lenzencoders.com>
License: MIT License
License-File: LICENSE
Keywords: angle,automation,biss,biss encoder,biss-c,calibration,embedded systems,encoder,firmware,flashtool,hardware,lenz,motion control,serial communication,servomotor
Classifier: Development Status :: 4 - Beta
Classifier: Environment :: Console
Classifier: Intended Audience :: Developers
Classifier: Intended Audience :: Manufacturing
Classifier: License :: OSI Approved :: MIT License
Classifier: Natural Language :: English
Classifier: Operating System :: OS Independent
Classifier: Programming Language :: Python :: 3
Classifier: Topic :: Communications
Classifier: Topic :: Scientific/Engineering :: Electronic Design Automation (EDA)
Classifier: Topic :: Scientific/Engineering :: Interface Engine/Protocol Translator
Classifier: Topic :: Software Development :: Embedded Systems
Classifier: Topic :: Software Development :: Libraries
Classifier: Topic :: System :: Hardware
Classifier: Topic :: Utilities
Requires-Python: >=3.8
Requires-Dist: colorama>=0.4.6
Requires-Dist: numpy>=1.21.0
Requires-Dist: pyserial>=3.5
